varsguard/__init__.py
varsguard/cli.py
varsguard-0.0.12.dist-info/LICENSE
varsguard-0.0.12.dist-info/METADATA
varsguard-0.0.12.dist-info/WHEEL
varsguard-0.0.12.dist-info/entry_points.txt
varsguard-0.0.12.dist-info/top_level.txt
varsguard-0.0.12.dist-info/RECORD
