Metadata-Version: 2.1
Name: varsguard
Version: 0.0.12
Summary: Python wrapper for the VarsGuard CLI tool.
Home-page: https://github.com/yessine-rebhi/varsguard-python
Author: Yessin Rebhi
Author-email: rabhiyassin@gmail.com
Classifier: Programming Language :: Python :: 3
Classifier: License :: OSI Approved :: MIT License
Classifier: Operating System :: OS Independent
Requires-Python: >=3.6
License-File: LICENSE
